CHANGES.rst
LICENSE
MANIFEST.in
README.rst
requirements.txt
setup.cfg
setup.py
booby/__init__.py
booby/_utils.py
booby/decoders.py
booby/encoders.py
booby/errors.py
booby/fields.py
booby/helpers.py
booby/inspection.py
booby/mixins.py
booby/models.py
booby/validators.py
booby_ng.egg-info/PKG-INFO
booby_ng.egg-info/SOURCES.txt
booby_ng.egg-info/dependency_links.txt
booby_ng.egg-info/requires.txt
booby_ng.egg-info/top_level.txt