Metadata-Version: 1.1
Name: booby-ng
Version: 0.8.4
Summary: Data modeling and validation Python library
Home-page: https://github.com/cr0hn/booby
Author: Daniel Garcia (cr0hn)
Author-email: cr0hn@cr0hn.com
License: UNKNOWN
Platform: UNKNOWN
Classifier: Development Status :: 3 - Alpha
Classifier: Intended Audience :: Developers
Classifier: Natural Language :: English
Classifier: Operating System :: OS Independent
Classifier: Programming Language :: Python
Classifier: Programming Language :: Python :: 2.7
Classifier: Programming Language :: Python :: 3.3
Classifier: Programming Language :: Python :: 3.4
Classifier: Programming Language :: Python :: 3.5
Classifier: Topic :: Software Development :: Libraries :: Python Modules
